sdss_semaphore/__init__.py
sdss_semaphore/targeting.py
sdss_semaphore/etc/__init__.py
sdss_semaphore/etc/sdss5_target_1_with_groups.csv
sdss_semaphore/etc/sdss5_target_2_with_groups.csv
sdss_semaphore/etc/sdss5_target_3_with_groups.csv
sdss_semaphore/etc/sdss5_target_4_with_groups.csv
sdss_semaphore-0.2.8.dist-info/licenses/LICENSE.md
sdss_semaphore-0.2.8.dist-info/METADATA
sdss_semaphore-0.2.8.dist-info/WHEEL
sdss_semaphore-0.2.8.dist-info/top_level.txt
sdss_semaphore-0.2.8.dist-info/RECORD
